flask_serial/__init__.py
flask_serial-1.0.4.dist-info/LICENSE
flask_serial-1.0.4.dist-info/METADATA
flask_serial-1.0.4.dist-info/WHEEL
flask_serial-1.0.4.dist-info/top_level.txt
flask_serial-1.0.4.dist-info/RECORD
