Metadata-Version: 2.1
Name: flask-serial
Version: 1.0.4
Summary: Flask extension for the Serial
Home-page: https://github.com/RedFalsh/flask-serial.git
Author: Redfalsh
Author-email: 13693421942@163.com
License: MIT
Platform: any
Classifier: Development Status :: 5 - Production/Stable
Classifier: Environment :: Web Environment
Classifier: Intended Audience :: Developers
Classifier: License :: OSI Approved :: MIT License
Classifier: Programming Language :: Python
Classifier: Topic :: Internet :: WWW/HTTP :: Dynamic Content
Classifier: Topic :: Software Development :: Libraries :: Python Modules
Requires-Dist: Flask
Requires-Dist: typing
Requires-Dist: pyserial
